[
  {
    "title": "Raaz Aankhein Teri",
    "artist": "Unknown",
    "file": "Raaz%20Aankhein%20Teri.mp3",
    "url": "https://cdn.jsdelivr.net/gh/sejalprabhakaran/my-music-1/music/Raaz%20Aankhein%20Teri.mp3",
    "cover": "https://sejalprabhakaran.github.io/my-music-1/covers/Raaz%20Aankhein%20Teri.jpg"
  },
  {
    "title": "Rab Ka Shukrana",
    "artist": "Unknown",
    "file": "Rab%20Ka%20Shukrana.mp3",
    "url": "https://cdn.jsdelivr.net/gh/sejalprabhakaran/my-music-1/music/Rab%20Ka%20Shukrana.mp3",
    "cover": "https://sejalprabhakaran.github.io/my-music-1/covers/Rab%20Ka%20Shukrana.jpg"
  },
  {
    "title": "Radha Nachegi",
    "artist": "Unknown",
    "file": "Radha%20Nachegi.mp3",
    "url": "https://cdn.jsdelivr.net/gh/sejalprabhakaran/my-music-1/music/Radha%20Nachegi.mp3",
    "cover": "https://sejalprabhakaran.github.io/my-music-1/covers/Radha%20Nachegi.jpg"
  },
  {
    "title": "Raja Ko Rani Se",
    "artist": "Unknown",
    "file": "Raja%20Ko%20Rani%20Se.mp3",
    "url": "https://cdn.jsdelivr.net/gh/sejalprabhakaran/my-music-1/music/Raja%20Ko%20Rani%20Se.mp3",
    "cover": "https://sejalprabhakaran.github.io/my-music-1/covers/Raja%20Ko%20Rani%20Se.jpg"
  },
  {
    "title": "Ram Chahe Leela",
    "artist": "Unknown",
    "file": "Ram%20Chahe%20Leela.mp3",
    "url": "https://cdn.jsdelivr.net/gh/sejalprabhakaran/my-music-1/music/Ram%20Chahe%20Leela.mp3",
    "cover": "https://sejalprabhakaran.github.io/my-music-1/covers/Ram%20Chahe%20Leela.jpg"
  },
  {
    "title": "Rap Ka Mausam",
    "artist": "Unknown",
    "file": "Rap%20Ka%20Mausam.mp3",
    "url": "https://cdn.jsdelivr.net/gh/sejalprabhakaran/my-music-1/music/Rap%20Ka%20Mausam.mp3",
    "cover": "https://sejalprabhakaran.github.io/my-music-1/covers/Rap%20Ka%20Mausam.jpg"
  },
  {
    "title": "Rasiya",
    "artist": "Unknown",
    "file": "Rasiya.mp3",
    "url": "https://cdn.jsdelivr.net/gh/sejalprabhakaran/my-music-1/music/Rasiya.mp3",
    "cover": "https://sejalprabhakaran.github.io/my-music-1/covers/Rasiya.jpg"
  },
  {
    "title": "Rim Jhim",
    "artist": "Unknown",
    "file": "Rim%20Jhim.mp3",
    "url": "https://cdn.jsdelivr.net/gh/sejalprabhakaran/my-music-1/music/Rim%20Jhim.mp3",
    "cover": "https://sejalprabhakaran.github.io/my-music-1/covers/Rim%20Jhim.jpg"
  },
  {
    "title": "Roi Na Je Yaad Meri Aayi Ve Roi na",
    "artist": "Unknown",
    "file": "Roi%20Na%20Je%20Yaad%20Meri%20Aayi%20Ve%20Roi%20na.mp3",
    "url": "https://cdn.jsdelivr.net/gh/sejalprabhakaran/my-music-1/music/Roi%20Na%20Je%20Yaad%20Meri%20Aayi%20Ve%20Roi%20na.mp3",
    "cover": "https://sejalprabhakaran.github.io/my-music-1/covers/Roi%20Na%20Je%20Yaad%20Meri%20Aayi%20Ve%20Roi%20na.jpg"
  },
  {
    "title": "Rote Hue Aate Hain",
    "artist": "Unknown",
    "file": "Rote%20Hue%20Aate%20Hain.mp3",
    "url": "https://cdn.jsdelivr.net/gh/sejalprabhakaran/my-music-1/music/Rote%20Hue%20Aate%20Hain.mp3",
    "cover": "https://sejalprabhakaran.github.io/my-music-1/covers/Rote%20Hue%20Aate%20Hain.jpg"
  },
  {
    "title": "Rusya Na Kar",
    "artist": "Unknown",
    "file": "Rusya%20Na%20Kar.mp3",
    "url": "https://cdn.jsdelivr.net/gh/sejalprabhakaran/my-music-1/music/Rusya%20Na%20Kar.mp3",
    "cover": "https://sejalprabhakaran.github.io/my-music-1/covers/Rusya%20Na%20Kar.jpg"
  },
  {
    "title": "Saagar Jaisi Aankhon Wali",
    "artist": "Unknown",
    "file": "Saagar%20Jaisi%20Aankhon%20Wali.mp3",
    "url": "https://cdn.jsdelivr.net/gh/sejalprabhakaran/my-music-1/music/Saagar%20Jaisi%20Aankhon%20Wali.mp3",
    "cover": "https://sejalprabhakaran.github.io/my-music-1/covers/Saagar%20Jaisi%20Aankhon%20Wali.jpg"
  },
  {
    "title": "Saami Saami Hindi",
    "artist": "Unknown",
    "file": "Saami%20Saami%20Hindi.mp3",
    "url": "https://cdn.jsdelivr.net/gh/sejalprabhakaran/my-music-1/music/Saami%20Saami%20Hindi.mp3",
    "cover": "https://sejalprabhakaran.github.io/my-music-1/covers/Saami%20Saami%20Hindi.jpg"
  },
  {
    "title": "Saans",
    "artist": "Unknown",
    "file": "Saans.mp3",
    "url": "https://cdn.jsdelivr.net/gh/sejalprabhakaran/my-music-1/music/Saans.mp3",
    "cover": "https://sejalprabhakaran.github.io/my-music-1/covers/Saans.jpg"
  },
  {
    "title": "Saanson Ke",
    "artist": "Unknown",
    "file": "Saanson%20Ke.mp3",
    "url": "https://cdn.jsdelivr.net/gh/sejalprabhakaran/my-music-1/music/Saanson%20Ke.mp3",
    "cover": "https://sejalprabhakaran.github.io/my-music-1/covers/Saanson%20Ke.jpg"
  },
  {
    "title": "Saanson Ko",
    "artist": "Unknown",
    "file": "Saanson%20Ko.mp3",
    "url": "https://cdn.jsdelivr.net/gh/sejalprabhakaran/my-music-1/music/Saanson%20Ko.mp3",
    "cover": "https://sejalprabhakaran.github.io/my-music-1/covers/Saanson%20Ko.jpg"
  },
  {
    "title": "Saaton Janam Main Tere Dilwale",
    "artist": "Unknown",
    "file": "Saaton%20Janam%20Main%20Tere%20Dilwale.mp3",
    "url": "https://cdn.jsdelivr.net/gh/sejalprabhakaran/my-music-1/music/Saaton%20Janam%20Main%20Tere%20Dilwale.mp3",
    "cover": "https://sejalprabhakaran.github.io/my-music-1/covers/Saaton%20Janam%20Main%20Tere%20Dilwale.jpg"
  },
  {
    "title": "Saaton Janam Main Tere",
    "artist": "Unknown",
    "file": "Saaton%20Janam%20Main%20Tere.mp3",
    "url": "https://cdn.jsdelivr.net/gh/sejalprabhakaran/my-music-1/music/Saaton%20Janam%20Main%20Tere.mp3",
    "cover": "https://sejalprabhakaran.github.io/my-music-1/covers/Saaton%20Janam%20Main%20Tere.jpg"
  },
  {
    "title": "Saawan Bairi",
    "artist": "Unknown",
    "file": "Saawan%20Bairi.mp3",
    "url": "https://cdn.jsdelivr.net/gh/sejalprabhakaran/my-music-1/music/Saawan%20Bairi.mp3",
    "cover": "https://sejalprabhakaran.github.io/my-music-1/covers/Saawan%20Bairi.jpg"
  },
  {
    "title": "Sab Tera",
    "artist": "Unknown",
    "file": "Sab%20Tera.mp3",
    "url": "https://cdn.jsdelivr.net/gh/sejalprabhakaran/my-music-1/music/Sab%20Tera.mp3",
    "cover": "https://sejalprabhakaran.github.io/my-music-1/covers/Sab%20Tera.jpg"
  },
  {
    "title": "Sagar Jaisi Aankhon Wali",
    "artist": "Unknown",
    "file": "Sagar%20Jaisi%20Aankhon%20Wali.mp3",
    "url": "https://cdn.jsdelivr.net/gh/sejalprabhakaran/my-music-1/music/Sagar%20Jaisi%20Aankhon%20Wali.mp3",
    "cover": "https://sejalprabhakaran.github.io/my-music-1/covers/Sagar%20Jaisi%20Aankhon%20Wali.jpg"
  },
  {
    "title": "Sagar Sung Kinare Hain",
    "artist": "Unknown",
    "file": "Sagar%20Sung%20Kinare%20Hain.mp3",
    "url": "https://cdn.jsdelivr.net/gh/sejalprabhakaran/my-music-1/music/Sagar%20Sung%20Kinare%20Hain.mp3",
    "cover": "https://sejalprabhakaran.github.io/my-music-1/covers/Sagar%20Sung%20Kinare%20Hain.jpg"
  },
  {
    "title": "Saiyaara",
    "artist": "Unknown",
    "file": "Saiyaara.mp3",
    "url": "https://cdn.jsdelivr.net/gh/sejalprabhakaran/my-music-1/music/Saiyaara.mp3",
    "cover": "https://sejalprabhakaran.github.io/my-music-1/covers/Saiyaara.jpg"
  },
  {
    "title": "Salamat",
    "artist": "Unknown",
    "file": "Salamat.mp3",
    "url": "https://cdn.jsdelivr.net/gh/sejalprabhakaran/my-music-1/music/Salamat.mp3",
    "cover": "https://sejalprabhakaran.github.io/my-music-1/covers/Salamat.jpg"
  },
  {
    "title": "Samajh Kar Chand Jis Ko",
    "artist": "Unknown",
    "file": "Samajh%20Kar%20Chand%20Jis%20Ko.mp3",
    "url": "https://cdn.jsdelivr.net/gh/sejalprabhakaran/my-music-1/music/Samajh%20Kar%20Chand%20Jis%20Ko.mp3",
    "cover": "https://sejalprabhakaran.github.io/my-music-1/covers/Samajh%20Kar%20Chand%20Jis%20Ko.jpg"
  },
  {
    "title": "Sanam Re",
    "artist": "Unknown",
    "file": "Sanam%20Re.mp3",
    "url": "https://cdn.jsdelivr.net/gh/sejalprabhakaran/my-music-1/music/Sanam%20Re.mp3",
    "cover": "https://sejalprabhakaran.github.io/my-music-1/covers/Sanam%20Re.jpg"
  },
  {
    "title": "Sanam Teri Kasam",
    "artist": "Unknown",
    "file": "Sanam%20Teri%20Kasam.mp3",
    "url": "https://cdn.jsdelivr.net/gh/sejalprabhakaran/my-music-1/music/Sanam%20Teri%20Kasam.mp3",
    "cover": "https://sejalprabhakaran.github.io/my-music-1/covers/Sanam%20Teri%20Kasam.jpg"
  },
  {
    "title": "Sandeshe Aate Hain",
    "artist": "Unknown",
    "file": "Sandeshe%20Aate%20Hain.mp3",
    "url": "https://cdn.jsdelivr.net/gh/sejalprabhakaran/my-music-1/music/Sandeshe%20Aate%20Hain.mp3",
    "cover": "https://sejalprabhakaran.github.io/my-music-1/covers/Sandeshe%20Aate%20Hain.jpg"
  },
  {
    "title": "Sanu Kehndi",
    "artist": "Unknown",
    "file": "Sanu%20Kehndi.mp3",
    "url": "https://cdn.jsdelivr.net/gh/sejalprabhakaran/my-music-1/music/Sanu%20Kehndi.mp3",
    "cover": "https://sejalprabhakaran.github.io/my-music-1/covers/Sanu%20Kehndi.jpg"
  },
  {
    "title": "Sawan Aaya Hai",
    "artist": "Unknown",
    "file": "Sawan%20Aaya%20Hai.mp3",
    "url": "https://cdn.jsdelivr.net/gh/sejalprabhakaran/my-music-1/music/Sawan%20Aaya%20Hai.mp3",
    "cover": "https://sejalprabhakaran.github.io/my-music-1/covers/Sawan%20Aaya%20Hai.jpg"
  },
  {
    "title": "Second Hand Jawaani",
    "artist": "Unknown",
    "file": "Second%20Hand%20Jawaani.mp3",
    "url": "https://cdn.jsdelivr.net/gh/sejalprabhakaran/my-music-1/music/Second%20Hand%20Jawaani.mp3",
    "cover": "https://sejalprabhakaran.github.io/my-music-1/covers/Second%20Hand%20Jawaani.jpg"
  },
  {
    "title": "Seenay Par Rakh Kar Sar Ko",
    "artist": "Unknown",
    "file": "Seenay%20Par%20Rakh%20Kar%20Sar%20Ko.mp3",
    "url": "https://cdn.jsdelivr.net/gh/sejalprabhakaran/my-music-1/music/Seenay%20Par%20Rakh%20Kar%20Sar%20Ko.mp3",
    "cover": "https://sejalprabhakaran.github.io/my-music-1/covers/Seenay%20Par%20Rakh%20Kar%20Sar%20Ko.jpg"
  },
  {
    "title": "Selfie Le Le Re",
    "artist": "Unknown",
    "file": "Selfie%20Le%20Le%20Re.mp3",
    "url": "https://cdn.jsdelivr.net/gh/sejalprabhakaran/my-music-1/music/Selfie%20Le%20Le%20Re.mp3",
    "cover": "https://sejalprabhakaran.github.io/my-music-1/covers/Selfie%20Le%20Le%20Re.jpg"
  },
  {
    "title": "Shayad Meri Shadi Ka Khayal",
    "artist": "Unknown",
    "file": "Shayad%20Meri%20Shadi%20Ka%20Khayal.mp3",
    "url": "https://cdn.jsdelivr.net/gh/sejalprabhakaran/my-music-1/music/Shayad%20Meri%20Shadi%20Ka%20Khayal.mp3",
    "cover": "https://sejalprabhakaran.github.io/my-music-1/covers/Shayad%20Meri%20Shadi%20Ka%20Khayal.jpg"
  },
  {
    "title": "Shayad Tu Mujhse Pyar Karti Hai",
    "artist": "Unknown",
    "file": "Shayad%20Tu%20Mujhse%20Pyar%20Karti%20Hai.mp3",
    "url": "https://cdn.jsdelivr.net/gh/sejalprabhakaran/my-music-1/music/Shayad%20Tu%20Mujhse%20Pyar%20Karti%20Hai.mp3",
    "cover": "https://sejalprabhakaran.github.io/my-music-1/covers/Shayad%20Tu%20Mujhse%20Pyar%20Karti%20Hai.jpg"
  },
  {
    "title": "Shayad",
    "artist": "Unknown",
    "file": "Shayad.mp3",
    "url": "https://cdn.jsdelivr.net/gh/sejalprabhakaran/my-music-1/music/Shayad.mp3",
    "cover": "https://sejalprabhakaran.github.io/my-music-1/covers/Shayad.jpg"
  },
  {
    "title": "Shikwa Nahin Kisi Se",
    "artist": "Unknown",
    "file": "Shikwa%20Nahin%20Kisi%20Se.mp3",
    "url": "https://cdn.jsdelivr.net/gh/sejalprabhakaran/my-music-1/music/Shikwa%20Nahin%20Kisi%20Se.mp3",
    "cover": "https://sejalprabhakaran.github.io/my-music-1/covers/Shikwa%20Nahin%20Kisi%20Se.jpg"
  },
  {
    "title": "Shivam",
    "artist": "Unknown",
    "file": "Shivam.mp3",
    "url": "https://cdn.jsdelivr.net/gh/sejalprabhakaran/my-music-1/music/Shivam.mp3",
    "cover": "https://sejalprabhakaran.github.io/my-music-1/covers/Shivam.jpg"
  },
  {
    "title": "So Gaya Yeh Jahan",
    "artist": "Unknown",
    "file": "So%20Gaya%20Yeh%20Jahan.mp3",
    "url": "https://cdn.jsdelivr.net/gh/sejalprabhakaran/my-music-1/music/So%20Gaya%20Yeh%20Jahan.mp3",
    "cover": "https://sejalprabhakaran.github.io/my-music-1/covers/So%20Gaya%20Yeh%20Jahan.jpg"
  },
  {
    "title": "Soch Liya",
    "artist": "Unknown",
    "file": "Soch%20Liya.mp3",
    "url": "https://cdn.jsdelivr.net/gh/sejalprabhakaran/my-music-1/music/Soch%20Liya.mp3",
    "cover": "https://sejalprabhakaran.github.io/my-music-1/covers/Soch%20Liya.jpg"
  },
  {
    "title": "Soch Na Sake",
    "artist": "Unknown",
    "file": "Soch%20Na%20Sake.mp3",
    "url": "https://cdn.jsdelivr.net/gh/sejalprabhakaran/my-music-1/music/Soch%20Na%20Sake.mp3",
    "cover": "https://sejalprabhakaran.github.io/my-music-1/covers/Soch%20Na%20Sake.jpg"
  },
  {
    "title": "Soch",
    "artist": "Unknown",
    "file": "Soch.mp3",
    "url": "https://cdn.jsdelivr.net/gh/sejalprabhakaran/my-music-1/music/Soch.mp3",
    "cover": "https://sejalprabhakaran.github.io/my-music-1/covers/Soch.jpg"
  },
  {
    "title": "Soja Zara",
    "artist": "Unknown",
    "file": "Soja%20Zara.mp3",
    "url": "https://cdn.jsdelivr.net/gh/sejalprabhakaran/my-music-1/music/Soja%20Zara.mp3",
    "cover": "https://sejalprabhakaran.github.io/my-music-1/covers/Soja%20Zara.jpg"
  },
  {
    "title": "Sona Kitna Sona Hai",
    "artist": "Unknown",
    "file": "Sona%20Kitna%20Sona%20Hai.mp3",
    "url": "https://cdn.jsdelivr.net/gh/sejalprabhakaran/my-music-1/music/Sona%20Kitna%20Sona%20Hai.mp3",
    "cover": "https://sejalprabhakaran.github.io/my-music-1/covers/Sona%20Kitna%20Sona%20Hai.jpg"
  },
  {
    "title": "Speaker Phat Jaaye",
    "artist": "Unknown",
    "file": "Speaker%20Phat%20Jaaye.mp3",
    "url": "https://cdn.jsdelivr.net/gh/sejalprabhakaran/my-music-1/music/Speaker%20Phat%20Jaaye.mp3",
    "cover": "https://sejalprabhakaran.github.io/my-music-1/covers/Speaker%20Phat%20Jaaye.jpg"
  },
  {
    "title": "Srivalli",
    "artist": "Unknown",
    "file": "Srivalli.mp3",
    "url": "https://cdn.jsdelivr.net/gh/sejalprabhakaran/my-music-1/music/Srivalli.mp3",
    "cover": "https://sejalprabhakaran.github.io/my-music-1/covers/Srivalli.jpg"
  },
  {
    "title": "Stay",
    "artist": "Unknown",
    "file": "Stay.mp3",
    "url": "https://cdn.jsdelivr.net/gh/sejalprabhakaran/my-music-1/music/Stay.mp3",
    "cover": "https://sejalprabhakaran.github.io/my-music-1/covers/Stay.jpg"
  },
  {
    "title": "Stop That",
    "artist": "Unknown",
    "file": "Stop%20That.mp3",
    "url": "https://cdn.jsdelivr.net/gh/sejalprabhakaran/my-music-1/music/Stop%20That.mp3",
    "cover": "https://sejalprabhakaran.github.io/my-music-1/covers/Stop%20That.jpg"
  },
  {
    "title": "Subhan Allah",
    "artist": "Unknown",
    "file": "Subhan%20Allah.mp3",
    "url": "https://cdn.jsdelivr.net/gh/sejalprabhakaran/my-music-1/music/Subhan%20Allah.mp3",
    "cover": "https://sejalprabhakaran.github.io/my-music-1/covers/Subhan%20Allah.jpg"
  },
  {
    "title": "Sun Saathiya",
    "artist": "Unknown",
    "file": "Sun%20Saathiya.mp3",
    "url": "https://cdn.jsdelivr.net/gh/sejalprabhakaran/my-music-1/music/Sun%20Saathiya.mp3",
    "cover": "https://sejalprabhakaran.github.io/my-music-1/covers/Sun%20Saathiya.jpg"
  },
  {
    "title": "Sun Sun Sun Barsaat Ki Dhun Sun",
    "artist": "Unknown",
    "file": "Sun%20Sun%20Sun%20Barsaat%20Ki%20Dhun%20Sun.mp3",
    "url": "https://cdn.jsdelivr.net/gh/sejalprabhakaran/my-music-1/music/Sun%20Sun%20Sun%20Barsaat%20Ki%20Dhun%20Sun.mp3",
    "cover": "https://sejalprabhakaran.github.io/my-music-1/covers/Sun%20Sun%20Sun%20Barsaat%20Ki%20Dhun%20Sun.jpg"
  },
  {
    "title": "Suna Hai Tere Dil Pe Mera Kahin Na Kahin Naam Hai Likha",
    "artist": "Unknown",
    "file": "Suna%20Hai%20Tere%20Dil%20Pe%20Mera%20Kahin%20Na%20Kahin%20Naam%20Hai%20Likha.mp3",
    "url": "https://cdn.jsdelivr.net/gh/sejalprabhakaran/my-music-1/music/Suna%20Hai%20Tere%20Dil%20Pe%20Mera%20Kahin%20Na%20Kahin%20Naam%20Hai%20Likha.mp3",
    "cover": "https://sejalprabhakaran.github.io/my-music-1/covers/Suna%20Hai%20Tere%20Dil%20Pe%20Mera%20Kahin%20Na%20Kahin%20Naam%20Hai%20Likha.jpg"
  },
  {
    "title": "Suna Hai",
    "artist": "Unknown",
    "file": "Suna%20Hai.mp3",
    "url": "https://cdn.jsdelivr.net/gh/sejalprabhakaran/my-music-1/music/Suna%20Hai.mp3",
    "cover": "https://sejalprabhakaran.github.io/my-music-1/covers/Suna%20Hai.jpg"
  },
  {
    "title": "Suniye To Rukiye To Kyon Hain Kafaa",
    "artist": "Unknown",
    "file": "Suniye%20To%20Rukiye%20To%20Kyon%20Hain%20Kafaa.mp3",
    "url": "https://cdn.jsdelivr.net/gh/sejalprabhakaran/my-music-1/music/Suniye%20To%20Rukiye%20To%20Kyon%20Hain%20Kafaa.mp3",
    "cover": "https://sejalprabhakaran.github.io/my-music-1/covers/Suniye%20To%20Rukiye%20To%20Kyon%20Hain%20Kafaa.jpg"
  },
  {
    "title": "Sunn Raha Hai",
    "artist": "Unknown",
    "file": "Sunn%20Raha%20Hai.mp3",
    "url": "https://cdn.jsdelivr.net/gh/sejalprabhakaran/my-music-1/music/Sunn%20Raha%20Hai.mp3",
    "cover": "https://sejalprabhakaran.github.io/my-music-1/covers/Sunn%20Raha%20Hai.jpg"
  },
  {
    "title": "Superman",
    "artist": "Unknown",
    "file": "Superman.mp3",
    "url": "https://cdn.jsdelivr.net/gh/sejalprabhakaran/my-music-1/music/Superman.mp3",
    "cover": "https://sejalprabhakaran.github.io/my-music-1/covers/Superman.jpg"
  },
  {
    "title": "Tabaah Ho Gaye",
    "artist": "Unknown",
    "file": "Tabaah%20Ho%20Gaye.mp3",
    "url": "https://cdn.jsdelivr.net/gh/sejalprabhakaran/my-music-1/music/Tabaah%20Ho%20Gaye.mp3",
    "cover": "https://sejalprabhakaran.github.io/my-music-1/covers/Tabaah%20Ho%20Gaye.jpg"
  },
  {
    "title": "Tabah",
    "artist": "Unknown",
    "file": "Tabah.mp3",
    "url": "https://cdn.jsdelivr.net/gh/sejalprabhakaran/my-music-1/music/Tabah.mp3",
    "cover": "https://sejalprabhakaran.github.io/my-music-1/covers/Tabah.jpg"
  },
  {
    "title": "Tanhaai",
    "artist": "Unknown",
    "file": "Tanhaai.mp3",
    "url": "https://cdn.jsdelivr.net/gh/sejalprabhakaran/my-music-1/music/Tanhaai.mp3",
    "cover": "https://sejalprabhakaran.github.io/my-music-1/covers/Tanhaai.jpg"
  },
  {
    "title": "Tarasti Hai Nigahen",
    "artist": "Unknown",
    "file": "Tarasti%20Hai%20Nigahen.mp3",
    "url": "https://cdn.jsdelivr.net/gh/sejalprabhakaran/my-music-1/music/Tarasti%20Hai%20Nigahen.mp3",
    "cover": "https://sejalprabhakaran.github.io/my-music-1/covers/Tarasti%20Hai%20Nigahen.jpg"
  },
  {
    "title": "Tarif Kya Karoon",
    "artist": "Unknown",
    "file": "Tarif%20Kya%20Karoon.mp3",
    "url": "https://cdn.jsdelivr.net/gh/sejalprabhakaran/my-music-1/music/Tarif%20Kya%20Karoon.mp3",
    "cover": "https://sejalprabhakaran.github.io/my-music-1/covers/Tarif%20Kya%20Karoon.jpg"
  },
  {
    "title": "Tauba Ye Matwali Chaal",
    "artist": "Unknown",
    "file": "Tauba%20Ye%20Matwali%20Chaal.mp3",
    "url": "https://cdn.jsdelivr.net/gh/sejalprabhakaran/my-music-1/music/Tauba%20Ye%20Matwali%20Chaal.mp3",
    "cover": "https://sejalprabhakaran.github.io/my-music-1/covers/Tauba%20Ye%20Matwali%20Chaal.jpg"
  },
  {
    "title": "Tera Baap Aaya",
    "artist": "Unknown",
    "file": "Tera%20Baap%20Aaya.mp3",
    "url": "https://cdn.jsdelivr.net/gh/sejalprabhakaran/my-music-1/music/Tera%20Baap%20Aaya.mp3",
    "cover": "https://sejalprabhakaran.github.io/my-music-1/covers/Tera%20Baap%20Aaya.jpg"
  },
  {
    "title": "Tera Chehra",
    "artist": "Unknown",
    "file": "Tera%20Chehra.mp3",
    "url": "https://cdn.jsdelivr.net/gh/sejalprabhakaran/my-music-1/music/Tera%20Chehra.mp3",
    "cover": "https://sejalprabhakaran.github.io/my-music-1/covers/Tera%20Chehra.jpg"
  },
  {
    "title": "Tera Hua",
    "artist": "Unknown",
    "file": "Tera%20Hua.mp3",
    "url": "https://cdn.jsdelivr.net/gh/sejalprabhakaran/my-music-1/music/Tera%20Hua.mp3",
    "cover": "https://sejalprabhakaran.github.io/my-music-1/covers/Tera%20Hua.jpg"
  },
  {
    "title": "Tera Saath Hai Kitna Pyaara",
    "artist": "Unknown",
    "file": "Tera%20Saath%20Hai%20Kitna%20Pyaara.mp3",
    "url": "https://cdn.jsdelivr.net/gh/sejalprabhakaran/my-music-1/music/Tera%20Saath%20Hai%20Kitna%20Pyaara.mp3",
    "cover": "https://sejalprabhakaran.github.io/my-music-1/covers/Tera%20Saath%20Hai%20Kitna%20Pyaara.jpg"
  },
  {
    "title": "Tera Sath Hai Kitna",
    "artist": "Unknown",
    "file": "Tera%20Sath%20Hai%20Kitna.mp3",
    "url": "https://cdn.jsdelivr.net/gh/sejalprabhakaran/my-music-1/music/Tera%20Sath%20Hai%20Kitna.mp3",
    "cover": "https://sejalprabhakaran.github.io/my-music-1/covers/Tera%20Sath%20Hai%20Kitna.jpg"
  },
  {
    "title": "Tera nam dil rakh diya",
    "artist": "Unknown",
    "file": "Tera%20nam%20dil%20rakh%20diya.mp3",
    "url": "https://cdn.jsdelivr.net/gh/sejalprabhakaran/my-music-1/music/Tera%20nam%20dil%20rakh%20diya.mp3",
    "cover": "https://sejalprabhakaran.github.io/my-music-1/covers/Tera%20nam%20dil%20rakh%20diya.jpg"
  },
  {
    "title": "Tere Bin Jiya Na Jaye",
    "artist": "Unknown",
    "file": "Tere%20Bin%20Jiya%20Na%20Jaye.mp3",
    "url": "https://cdn.jsdelivr.net/gh/sejalprabhakaran/my-music-1/music/Tere%20Bin%20Jiya%20Na%20Jaye.mp3",
    "cover": "https://sejalprabhakaran.github.io/my-music-1/covers/Tere%20Bin%20Jiya%20Na%20Jaye.jpg"
  },
  {
    "title": "Tere Bin Nahi Laage",
    "artist": "Unknown",
    "file": "Tere%20Bin%20Nahi%20Laage.mp3",
    "url": "https://cdn.jsdelivr.net/gh/sejalprabhakaran/my-music-1/music/Tere%20Bin%20Nahi%20Laage.mp3",
    "cover": "https://sejalprabhakaran.github.io/my-music-1/covers/Tere%20Bin%20Nahi%20Laage.jpg"
  },
  {
    "title": "Tere Bina Jeena Bhi Hai Kya Jeena",
    "artist": "Unknown",
    "file": "Tere%20Bina%20Jeena%20Bhi%20Hai%20Kya%20Jeena.mp3",
    "url": "https://cdn.jsdelivr.net/gh/sejalprabhakaran/my-music-1/music/Tere%20Bina%20Jeena%20Bhi%20Hai%20Kya%20Jeena.mp3",
    "cover": "https://sejalprabhakaran.github.io/my-music-1/covers/Tere%20Bina%20Jeena%20Bhi%20Hai%20Kya%20Jeena.jpg"
  },
  {
    "title": "Tere Dar Pe Sanam",
    "artist": "Unknown",
    "file": "Tere%20Dar%20Pe%20Sanam.mp3",
    "url": "https://cdn.jsdelivr.net/gh/sejalprabhakaran/my-music-1/music/Tere%20Dar%20Pe%20Sanam.mp3",
    "cover": "https://sejalprabhakaran.github.io/my-music-1/covers/Tere%20Dar%20Pe%20Sanam.jpg"
  },
  {
    "title": "Tere Dard Se Dil",
    "artist": "Unknown",
    "file": "Tere%20Dard%20Se%20Dil.mp3",
    "url": "https://cdn.jsdelivr.net/gh/sejalprabhakaran/my-music-1/music/Tere%20Dard%20Se%20Dil.mp3",
    "cover": "https://sejalprabhakaran.github.io/my-music-1/covers/Tere%20Dard%20Se%20Dil.jpg"
  },
  {
    "title": "Tere Jism 2",
    "artist": "Unknown",
    "file": "Tere%20Jism%202.mp3",
    "url": "https://cdn.jsdelivr.net/gh/sejalprabhakaran/my-music-1/music/Tere%20Jism%202.mp3",
    "cover": "https://sejalprabhakaran.github.io/my-music-1/covers/Tere%20Jism%202.jpg"
  },
  {
    "title": "Tere Liye",
    "artist": "Unknown",
    "file": "Tere%20Liye.mp3",
    "url": "https://cdn.jsdelivr.net/gh/sejalprabhakaran/my-music-1/music/Tere%20Liye.mp3",
    "cover": "https://sejalprabhakaran.github.io/my-music-1/covers/Tere%20Liye.jpg"
  },
  {
    "title": "Tere Mast Mast Do Nain",
    "artist": "Unknown",
    "file": "Tere%20Mast%20Mast%20Do%20Nain.mp3",
    "url": "https://cdn.jsdelivr.net/gh/sejalprabhakaran/my-music-1/music/Tere%20Mast%20Mast%20Do%20Nain.mp3",
    "cover": "https://sejalprabhakaran.github.io/my-music-1/covers/Tere%20Mast%20Mast%20Do%20Nain.jpg"
  },
  {
    "title": "Tere Naam Female",
    "artist": "Unknown",
    "file": "Tere%20Naam%20Female.mp3",
    "url": "https://cdn.jsdelivr.net/gh/sejalprabhakaran/my-music-1/music/Tere%20Naam%20Female.mp3",
    "cover": "https://sejalprabhakaran.github.io/my-music-1/covers/Tere%20Naam%20Female.jpg"
  },
  {
    "title": "Tere Naam",
    "artist": "Unknown",
    "file": "Tere%20Naam.mp3",
    "url": "https://cdn.jsdelivr.net/gh/sejalprabhakaran/my-music-1/music/Tere%20Naam.mp3",
    "cover": "https://sejalprabhakaran.github.io/my-music-1/covers/Tere%20Naam.jpg"
  },
  {
    "title": "Tere Nalo Chaliye Haseen Koi Na",
    "artist": "Unknown",
    "file": "Tere%20Nalo%20Chaliye%20Haseen%20Koi%20Na.mp3",
    "url": "https://cdn.jsdelivr.net/gh/sejalprabhakaran/my-music-1/music/Tere%20Nalo%20Chaliye%20Haseen%20Koi%20Na.mp3",
    "cover": "https://sejalprabhakaran.github.io/my-music-1/covers/Tere%20Nalo%20Chaliye%20Haseen%20Koi%20Na.jpg"
  },
  {
    "title": "Tere Siva Jag Mein",
    "artist": "Unknown",
    "file": "Tere%20Siva%20Jag%20Mein.mp3",
    "url": "https://cdn.jsdelivr.net/gh/sejalprabhakaran/my-music-1/music/Tere%20Siva%20Jag%20Mein.mp3",
    "cover": "https://sejalprabhakaran.github.io/my-music-1/covers/Tere%20Siva%20Jag%20Mein.jpg"
  },
  {
    "title": "Teri Galiyon Mein Na Rakhein",
    "artist": "Unknown",
    "file": "Teri%20Galiyon%20Mein%20Na%20Rakhein.mp3",
    "url": "https://cdn.jsdelivr.net/gh/sejalprabhakaran/my-music-1/music/Teri%20Galiyon%20Mein%20Na%20Rakhein.mp3",
    "cover": "https://sejalprabhakaran.github.io/my-music-1/covers/Teri%20Galiyon%20Mein%20Na%20Rakhein.jpg"
  },
  {
    "title": "Teri Issi Aada Pe Sanam",
    "artist": "Unknown",
    "file": "Teri%20Issi%20Aada%20Pe%20Sanam.mp3",
    "url": "https://cdn.jsdelivr.net/gh/sejalprabhakaran/my-music-1/music/Teri%20Issi%20Aada%20Pe%20Sanam.mp3",
    "cover": "https://sejalprabhakaran.github.io/my-music-1/covers/Teri%20Issi%20Aada%20Pe%20Sanam.jpg"
  },
  {
    "title": "Teri Khushboo",
    "artist": "Unknown",
    "file": "Teri%20Khushboo.mp3",
    "url": "https://cdn.jsdelivr.net/gh/sejalprabhakaran/my-music-1/music/Teri%20Khushboo.mp3",
    "cover": "https://sejalprabhakaran.github.io/my-music-1/covers/Teri%20Khushboo.jpg"
  },
  {
    "title": "Teri Meri Kahaani",
    "artist": "Unknown",
    "file": "Teri%20Meri%20Kahaani.mp3",
    "url": "https://cdn.jsdelivr.net/gh/sejalprabhakaran/my-music-1/music/Teri%20Meri%20Kahaani.mp3",
    "cover": "https://sejalprabhakaran.github.io/my-music-1/covers/Teri%20Meri%20Kahaani.jpg"
  },
  {
    "title": "Teri Saanson Mein",
    "artist": "Unknown",
    "file": "Teri%20Saanson%20Mein.mp3",
    "url": "https://cdn.jsdelivr.net/gh/sejalprabhakaran/my-music-1/music/Teri%20Saanson%20Mein.mp3",
    "cover": "https://sejalprabhakaran.github.io/my-music-1/covers/Teri%20Saanson%20Mein.jpg"
  },
  {
    "title": "Teri Umeed Tera Intezaar",
    "artist": "Unknown",
    "file": "Teri%20Umeed%20Tera%20Intezaar.mp3",
    "url": "https://cdn.jsdelivr.net/gh/sejalprabhakaran/my-music-1/music/Teri%20Umeed%20Tera%20Intezaar.mp3",
    "cover": "https://sejalprabhakaran.github.io/my-music-1/covers/Teri%20Umeed%20Tera%20Intezaar.jpg"
  },
  {
    "title": "Teri Ungali Pakad Ke Chala",
    "artist": "Unknown",
    "file": "Teri%20Ungali%20Pakad%20Ke%20Chala.mp3",
    "url": "https://cdn.jsdelivr.net/gh/sejalprabhakaran/my-music-1/music/Teri%20Ungali%20Pakad%20Ke%20Chala.mp3",
    "cover": "https://sejalprabhakaran.github.io/my-music-1/covers/Teri%20Ungali%20Pakad%20Ke%20Chala.jpg"
  },
  {
    "title": "Teri Yaad Yaad Yaad",
    "artist": "Unknown",
    "file": "Teri%20Yaad%20Yaad%20Yaad.mp3",
    "url": "https://cdn.jsdelivr.net/gh/sejalprabhakaran/my-music-1/music/Teri%20Yaad%20Yaad%20Yaad.mp3",
    "cover": "https://sejalprabhakaran.github.io/my-music-1/covers/Teri%20Yaad%20Yaad%20Yaad.jpg"
  },
  {
    "title": "Teri Yaad",
    "artist": "Unknown",
    "file": "Teri%20Yaad.mp3",
    "url": "https://cdn.jsdelivr.net/gh/sejalprabhakaran/my-music-1/music/Teri%20Yaad.mp3",
    "cover": "https://sejalprabhakaran.github.io/my-music-1/covers/Teri%20Yaad.jpg"
  },
  {
    "title": "Teri Yaadon Se",
    "artist": "Unknown",
    "file": "Teri%20Yaadon%20Se.mp3",
    "url": "https://cdn.jsdelivr.net/gh/sejalprabhakaran/my-music-1/music/Teri%20Yaadon%20Se.mp3",
    "cover": "https://sejalprabhakaran.github.io/my-music-1/covers/Teri%20Yaadon%20Se.jpg"
  },
  {
    "title": "Terre Pyaar Mein",
    "artist": "Unknown",
    "file": "Terre%20Pyaar%20Mein.mp3",
    "url": "https://cdn.jsdelivr.net/gh/sejalprabhakaran/my-music-1/music/Terre%20Pyaar%20Mein.mp3",
    "cover": "https://sejalprabhakaran.github.io/my-music-1/covers/Terre%20Pyaar%20Mein.jpg"
  },
  {
    "title": "The Breakup Song",
    "artist": "Unknown",
    "file": "The%20Breakup%20Song.mp3",
    "url": "https://cdn.jsdelivr.net/gh/sejalprabhakaran/my-music-1/music/The%20Breakup%20Song.mp3",
    "cover": "https://sejalprabhakaran.github.io/my-music-1/covers/The%20Breakup%20Song.jpg"
  },
  {
    "title": "The Monster",
    "artist": "Unknown",
    "file": "The%20Monster.mp3",
    "url": "https://cdn.jsdelivr.net/gh/sejalprabhakaran/my-music-1/music/The%20Monster.mp3",
    "cover": "https://sejalprabhakaran.github.io/my-music-1/covers/The%20Monster.jpg"
  },
  {
    "title": "Thehro To Sahi",
    "artist": "Unknown",
    "file": "Thehro%20To%20Sahi.mp3",
    "url": "https://cdn.jsdelivr.net/gh/sejalprabhakaran/my-music-1/music/Thehro%20To%20Sahi.mp3",
    "cover": "https://sejalprabhakaran.github.io/my-music-1/covers/Thehro%20To%20Sahi.jpg"
  },
  {
    "title": "Theme of Dilwale",
    "artist": "Unknown",
    "file": "Theme%20of%20Dilwale.mp3",
    "url": "https://cdn.jsdelivr.net/gh/sejalprabhakaran/my-music-1/music/Theme%20of%20Dilwale.mp3",
    "cover": "https://sejalprabhakaran.github.io/my-music-1/covers/Theme%20of%20Dilwale.jpg"
  },
  {
    "title": "Thoda Thoda Pyaar Hua Tumse",
    "artist": "Unknown",
    "file": "Thoda%20Thoda%20Pyaar%20Hua%20Tumse.mp3",
    "url": "https://cdn.jsdelivr.net/gh/sejalprabhakaran/my-music-1/music/Thoda%20Thoda%20Pyaar%20Hua%20Tumse.mp3",
    "cover": "https://sejalprabhakaran.github.io/my-music-1/covers/Thoda%20Thoda%20Pyaar%20Hua%20Tumse.jpg"
  },
  {
    "title": "Thodi Der",
    "artist": "Unknown",
    "file": "Thodi%20Der.mp3",
    "url": "https://cdn.jsdelivr.net/gh/sejalprabhakaran/my-music-1/music/Thodi%20Der.mp3",
    "cover": "https://sejalprabhakaran.github.io/my-music-1/covers/Thodi%20Der.jpg"
  },
  {
    "title": "Tip Tip Barsa",
    "artist": "Unknown",
    "file": "Tip%20Tip%20Barsa.mp3",
    "url": "https://cdn.jsdelivr.net/gh/sejalprabhakaran/my-music-1/music/Tip%20Tip%20Barsa.mp3",
    "cover": "https://sejalprabhakaran.github.io/my-music-1/covers/Tip%20Tip%20Barsa.jpg"
  },
  {
    "title": "saaho",
    "artist": "Unknown",
    "file": "saaho.mp3",
    "url": "https://cdn.jsdelivr.net/gh/sejalprabhakaran/my-music-1/music/saaho.mp3",
    "cover": "https://sejalprabhakaran.github.io/my-music-1/covers/saaho.jpg"
  },
  {
    "title": "teri meri kahani",
    "artist": "Unknown",
    "file": "teri%20meri%20kahani.mp3",
    "url": "https://cdn.jsdelivr.net/gh/sejalprabhakaran/my-music-1/music/teri%20meri%20kahani.mp3",
    "cover": "https://sejalprabhakaran.github.io/my-music-1/covers/teri%20meri%20kahani.jpg"
  }
]
